kotokenizer/__init__.py
kotokenizer-0.1.1.dist-info/LICENSE
kotokenizer-0.1.1.dist-info/METADATA
kotokenizer-0.1.1.dist-info/WHEEL
kotokenizer-0.1.1.dist-info/top_level.txt
kotokenizer-0.1.1.dist-info/RECORD
